setup.py
constant_contact_python.egg-info/PKG-INFO
constant_contact_python.egg-info/SOURCES.txt
constant_contact_python.egg-info/dependency_links.txt
constant_contact_python.egg-info/not-zip-safe
constant_contact_python.egg-info/requires.txt
constant_contact_python.egg-info/top_level.txt
constantcontact/__init__.py