Metadata-Version: 1.1
Name: constant-contact-python
Version: 0.1.0
Summary: Python 3 api sdk for constantcontact.com
Home-page: UNKNOWN
Author: Jordan Clark
Author-email: jordan@blitzen.com
License: MIT
Platform: UNKNOWN
Classifier: Development Status :: 3 - Alpha
Classifier: Intended Audience :: Developers
Classifier: Natural Language :: English
Classifier: License :: OSI Approved :: MIT License
Classifier: Programming Language :: Python :: 3
